{
    "name": "Amenities",
    "load": "http://www.wynnlasvegas.com/Amenities",
    "delay": 0,
    "queries": [
        {
            "query": "a.menu-item.active",
            "property": "textContent",
            "name": "title"
        },
        {
            "query": "div.row.wlv-home-main div.home-main-img div.carousel-inner img",
            "property": "src",
            "name": "images"
        },
        {
            "query": "div.row.wlv-home-main div.content div.section-text, div.row.wlv-home-main div.content div.section-text p",
            "property": "textContent",
            "name": "description",
            "index": 0
        },
        {
            "name": "type",
            "value": "category"
        }
    ],
    "projectName": "www.wynnlasvegas.com",
    "cacheDir": "/Users/decky/Documents/nodejs/wynn/scraper/cache/www.wynnlasvegas.com",
    "id": 48,
    "pageResolved": true
}